{
  "id": "ess_1781075363356",
  "charName": "Ess",
  "playerName": "Jorja",
  "pinHash": "3d632c3b5f0ebc68d9847f6fd28c00bd07fd749891505049a38dee82d4025896",
  "createdAt": "2026-06-10T07:09:23.357Z",
  "class": "",
  "subclass": "",
  "race": "",
  "subrace": "",
  "level": 1,
  "xp": 0,
  "abilities": {
    "str": 10,
    "dex": 20,
    "con": 13,
    "int": 10,
    "wis": 18,
    "cha": 8
  },
  "hp_max": 0,
  "hp_current": 0,
  "hp_temp": 0,
  "hd_used": 0,
  "ac": 10,
  "speed": 30,
  "inspiration": false,
  "proficiencies": "",
  "languages": "",
  "features": "",
  "attacks": [],
  "equipment": [],
  "magic_items": [],
  "currency": {
    "cp": 0,
    "sp": 0,
    "ep": 0,
    "gp": 0,
    "pp": 0
  },
  "spells_prepared": [],
  "spell_slots_used": {},
  "death_saves": {
    "successes": 0,
    "failures": 0
  },
  "conditions": [],
  "exhaustion": 0,
  "background": "",
  "alignment": "True Neutral",
  "traits": "",
  "ideals": "",
  "bonds": "",
  "flaws": "",
  "backstory": "",
  "appearance": "",
  "history": "",
  "notes_bg": "",
  "notes": "",
  "goals": "",
  "enemies": "",
  "relationships": "",
  "secrets": "",
  "spells": {
    "known": [],
    "prepared": [],
    "spellbook": [],
    "featSpells": {}
  },
  "spell_notes": "",
  "class_choices": {},
  "resources": {},
  "featSlots": {},
  "_darkvision": 0,
  "_dmgres": [],
  "_customSpeed": false,
  "faith": "",
  "age": "",
  "height": "",
  "weight": "",
  "eyes": "",
  "hair": "",
  "skin": "",
  "gender": "",
  "holdings": "",
  "feats": [],
  "classes": [
    {
      "class": "",
      "subclass": "",
      "levels": [
        1
      ]
    }
  ],
  "levelPlan": {
    "1": ""
  },
  "abilityLayers": {
    "base": {
      "str": 10,
      "dex": 20,
      "con": 13,
      "int": 10,
      "wis": 18,
      "cha": 8
    },
    "background": {
      "str": 0,
      "dex": 0,
      "con": 0,
      "int": 0,
      "wis": 0,
      "cha": 0
    },
    "featSlots": {
      "str": 0,
      "dex": 0,
      "con": 0,
      "int": 0,
      "wis": 0,
      "cha": 0
    },
    "featDetail": {
      "str": 0,
      "dex": 0,
      "con": 0,
      "int": 0,
      "wis": 0,
      "cha": 0
    },
    "cap": {},
    "hardSet": {}
  },
  "magicItems": [],
  "_toughBonus": 0,
  "_hasDurable": false,
  "_featSpeedBonus": 0,
  "_hasObservant": false,
  "_alertBonus": 0,
  "weapons": [],
  "ammo": {
    "arrows": 20,
    "bolts": 0,
    "bullets": 0,
    "darts": 0,
    "needles": 0,
    "firearm_rounds": 0
  },
  "_activeEffects": {},
  "name": "Ess",
  "shield": false,
  "base_speed": 30,
  "saves_notes": "",
  "allies": ""
}